antsibull_build/__init__.py
antsibull_build/announcements.py
antsibull_build/ansible_core_reqs.py
antsibull_build/build_ansible_commands.py
antsibull_build/build_changelog.py
antsibull_build/build_data_lint.py
antsibull_build/build_data_reformat.py
antsibull_build/changelog.py
antsibull_build/constants.py
antsibull_build/dep_closure.py
antsibull_build/new_ansible.py
antsibull_build/py.typed
antsibull_build/pypi.py
antsibull_build/python_metadata.py
antsibull_build/sanity_tests.py
antsibull_build/tagging.py
antsibull_build/types.py
antsibull_build/versions.py
antsibull_build/_vendor/__init__.py
antsibull_build/_vendor/shutil.py
antsibull_build/cli/__init__.py
antsibull_build/cli/antsibull_build.py
antsibull_build/data/README_md.txt
antsibull_build/data/README_md.txt.license
antsibull_build/data/__init__.py
antsibull_build/data/ansible-community.py.j2
antsibull_build/data/ansible-forum-announcement.j2
antsibull_build/data/ansible-matrix-announcement.j2
antsibull_build/data/ansible-readme.rst
antsibull_build/data/ansible-release_py.j2
antsibull_build/data/ansible-setup_py.j2
antsibull_build/data/ansible-stub-setup.py
antsibull_build/data/build-ansible.sh.j2
antsibull_build/data/collection-readme.j2
antsibull_build/data/collection-setup_py.j2
antsibull_build/data/galaxy_yml.j2
antsibull_build/data/gplv3.txt
antsibull_build/data/gplv3.txt.license
antsibull_build/data/pyproject.toml
antsibull_build/data/debian/changelog.j2
antsibull_build/data/debian/control.j2
antsibull_build/data/debian/copyright
antsibull_build/data/debian/copyright.license
antsibull_build/data/debian/rules
antsibull_build/data/debian/rules.license
antsibull_build/from_source/__init__.py
antsibull_build/from_source/_utils.py
antsibull_build/from_source/clone.py
antsibull_build/from_source/commands.py
antsibull_build/from_source/exceptions.py
antsibull_build/from_source/verify.py
antsibull_build/utils/__init__.py
antsibull_build/utils/galaxy.py
antsibull_build/utils/get_pkg_data.py
antsibull_build-0.77.0.dist-info/METADATA
antsibull_build-0.77.0.dist-info/WHEEL
antsibull_build-0.77.0.dist-info/entry_points.txt
antsibull_build-0.77.0.dist-info/licenses/LICENSES/GPL-3.0-or-later.txt
antsibull_build-0.77.0.dist-info/licenses/LICENSES/Python-2.0.1.txt
antsibull_build-0.77.0.dist-info/RECORD
