Metadata-Version: 2.4
Name: antsibull-build
Version: 0.77.0
Summary: Tools for building the Ansible Community Distribution
Project-URL: Source code, https://github.com/ansible-community/antsibull-build
Project-URL: Code of Conduct, https://docs.ansible.com/projects/ansible/latest/community/code_of_conduct.html
Project-URL: Bug tracker, https://github.com/ansible-community/antsibull-build/issues
Project-URL: Changelog, https://github.com/ansible-community/antsibull-build/tree/main/CHANGELOG.md
Author-email: Toshio Kuratomi <a.badger@gmail.com>, Felix Fontein <felix@fontein.de>
Maintainer-email: Felix Fontein <felix@fontein.de>, Maxwell G <maxwell@gtmx.me>
License-Expression: GPL-3.0-or-later AND Python-2.0.1
License-File: LICENSES/GPL-3.0-or-later.txt
License-File: LICENSES/Python-2.0.1.txt
Classifier: Development Status :: 5 - Production/Stable
Classifier: Framework :: Ansible
Classifier: Intended Audience :: Developers
Classifier: Programming Language :: Python :: 3.9
Classifier: Programming Language :: Python :: 3.10
Classifier: Programming Language :: Python :: 3.11
Classifier: Programming Language :: Python :: 3.12
Classifier: Programming Language :: Python :: 3.13
Classifier: Typing :: Typed
Requires-Python: >=3.9
Requires-Dist: aiofiles
Requires-Dist: aiohttp>=3.0.0
Requires-Dist: antsibull-changelog>=0.34.0
Requires-Dist: antsibull-core<4.0.0,>=3.5.0
Requires-Dist: antsibull-docs-parser<2.0.0,>=1.1.0
Requires-Dist: antsibull-fileutils<2.0.0,>=1.0.0
Requires-Dist: asyncio-pool
Requires-Dist: build
Requires-Dist: jinja2
Requires-Dist: packaging>=20.0
Requires-Dist: pydantic<3,>=2
Requires-Dist: pyyaml
Requires-Dist: semantic-version
Requires-Dist: typing-extensions
Provides-Extra: all
Requires-Dist: pyperclip; extra == 'all'
Provides-Extra: clipboard
Requires-Dist: pyperclip; extra == 'clipboard'
Provides-Extra: codeqa
Requires-Dist: flake8>=3.8.0; extra == 'codeqa'
Requires-Dist: pylint; extra == 'codeqa'
Requires-Dist: reuse; extra == 'codeqa'
Provides-Extra: coverage
Requires-Dist: coverage[toml]; extra == 'coverage'
Provides-Extra: dev
Requires-Dist: asynctest; extra == 'dev'
Requires-Dist: coverage[toml]; extra == 'dev'
Requires-Dist: cryptography; extra == 'dev'
Requires-Dist: flake8>=3.8.0; extra == 'dev'
Requires-Dist: mypy; extra == 'dev'
Requires-Dist: nox; extra == 'dev'
Requires-Dist: pylint; extra == 'dev'
Requires-Dist: pyperclip; extra == 'dev'
Requires-Dist: pytest; extra == 'dev'
Requires-Dist: pytest-asyncio>=0.12; extra == 'dev'
Requires-Dist: pytest-cov; extra == 'dev'
Requires-Dist: pytest-error-for-skips; extra == 'dev'
Requires-Dist: reuse; extra == 'dev'
Requires-Dist: types-aiofiles; extra == 'dev'
Requires-Dist: types-docutils; extra == 'dev'
Requires-Dist: types-pyyaml; extra == 'dev'
Requires-Dist: types-setuptools; extra == 'dev'
Provides-Extra: formatters
Requires-Dist: black>=24; extra == 'formatters'
Requires-Dist: isort; extra == 'formatters'
Provides-Extra: test
Requires-Dist: asynctest; extra == 'test'
Requires-Dist: cryptography; extra == 'test'
Requires-Dist: pytest; extra == 'test'
Requires-Dist: pytest-asyncio>=0.12; extra == 'test'
Requires-Dist: pytest-cov; extra == 'test'
Requires-Dist: pytest-error-for-skips; extra == 'test'
Provides-Extra: typing
Requires-Dist: mypy; extra == 'typing'
Requires-Dist: pytest; extra == 'typing'
Requires-Dist: types-aiofiles; extra == 'typing'
Requires-Dist: types-docutils; extra == 'typing'
Requires-Dist: types-pyyaml; extra == 'typing'
Requires-Dist: types-setuptools; extra == 'typing'
